LICENSE
MANIFEST.in
README.md
setup.cfg
setup.py
sjsonrpc/__init__.py
sjsonrpc/exceptjsonrpc.py
sjsonrpc.egg-info/PKG-INFO
sjsonrpc.egg-info/SOURCES.txt
sjsonrpc.egg-info/dependency_links.txt
sjsonrpc.egg-info/requires.txt
sjsonrpc.egg-info/top_level.txt
sjsonrpc/asy/ConnectionControl.py
sjsonrpc/asy/ProxyObject.py
sjsonrpc/asy/RPC_Call.py
sjsonrpc/asy/RPC_Responser.py
sjsonrpc/asy/__init__.py
sjsonrpc/syn/ConnectionControl.py
sjsonrpc/syn/ProxyObject.py
sjsonrpc/syn/RPC_Call.py
sjsonrpc/syn/RPC_Responser.py
sjsonrpc/syn/__init__.py