Metadata-Version: 2.4
Name: sjsonrpc
Version: 2.0.2
Summary: Json RPC Python Wrapper class
Home-page: https://github.com/EduardoPagotto/sJsonRpc.git
Author: Eduardo Pagotto
Author-email: edupagotto@gmail.com
License: MIT License
Platform: any
Classifier: Development Status :: 4 - Beta
Classifier: Intended Audience :: Developers
Classifier: Topic :: File Formats :: JSON
Classifier: Topic :: Software Development :: Libraries
Classifier: Programming Language :: Python :: 3
Classifier: Operating System :: OS Independent
License-File: LICENSE
Requires-Dist: setuptools
Requires-Dist: typing_extensions
Requires-Dist: wheel
Dynamic: author
Dynamic: author-email
Dynamic: classifier
Dynamic: description
Dynamic: description-content-type
Dynamic: home-page
Dynamic: license
Dynamic: license-file
Dynamic: platform
Dynamic: requires-dist
Dynamic: summary
